LICENSE
README.md
setup.py
etudatasphere/DataSphereManager.py
etudatasphere/OperationManager.py
etudatasphere/__init__.py
etudatasphere/exceptions.py
etudatasphere/requests.py
etudatasphere/utils.py
etudatasphere.egg-info/PKG-INFO
etudatasphere.egg-info/SOURCES.txt
etudatasphere.egg-info/dependency_links.txt
etudatasphere.egg-info/requires.txt
etudatasphere.egg-info/top_level.txt
tests/test_etudatasphere.py